pyredraw/__init__.py
pyredraw/plotting.py
pyredraw/ts.py
pyredraw-0.2.2.dist-info/LICENSE
pyredraw-0.2.2.dist-info/WHEEL
pyredraw-0.2.2.dist-info/METADATA
pyredraw-0.2.2.dist-info/RECORD
