Metadata-Version: 2.1
Name: pyredraw
Version: 0.2.2
Summary: A python package for resampling statistical operations
License: MIT
Author: Elizabeth H. Camp
Requires-Python: >=3.9,<3.11
Classifier: License :: OSI Approved :: MIT License
Classifier: Programming Language :: Python :: 3
Classifier: Programming Language :: Python :: 3.9
Requires-Dist: matplotlib (>=3.6.2)
Requires-Dist: numpy (==1.23.5)
Requires-Dist: scipy (==1.8.1)
Requires-Dist: statsmodels (>=0.13.5,<0.14.0)
